pyTamil/__init__.py
pyTamil/thirukural.py
pyTamil-0.2.dist-info/LICENSE
pyTamil-0.2.dist-info/METADATA
pyTamil-0.2.dist-info/WHEEL
pyTamil-0.2.dist-info/top_level.txt
pyTamil-0.2.dist-info/RECORD
