Metadata-Version: 2.1
Name: pyTamil
Version: 0.2
Summary: A simple example package
Home-page: https://github.com/kamalkavin68/pyTamil
Author: kamalkavin96
Author-email: kamalkavin68@gmail.com
License: MIT
License-File: LICENSE
Requires-Dist: pydantic==2.9.1
